wallchart/__init__.py
wallchart/api.py
wallchart/db.py
wallchart/defaults.py
wallchart/static/bootstrap.min.css
wallchart/static/fuse.js
wallchart/static/style.css
wallchart/templates/admin.html
wallchart/templates/department.html
wallchart/templates/departments.html
wallchart/templates/departments_edit.html
wallchart/templates/find_worker.html
wallchart/templates/former.html
wallchart/templates/homepage.html
wallchart/templates/includes/message.html
wallchart/templates/layout.html
wallchart/templates/login.html
wallchart/templates/structure_test.html
wallchart/templates/structure_tests.html
wallchart/templates/upload_record.html
wallchart/templates/users.html
wallchart/templates/worker.html
wallchart/templates/workplaces.html
wallchart/templates/workplaces_edit.html
wallchart/util.py
wallchart/views.py
wallchart-0.0.14.dist-info/METADATA
wallchart-0.0.14.dist-info/WHEEL
wallchart-0.0.14.dist-info/RECORD
