Metadata-Version: 2.1
Name: wallchart
Version: 0.0.14
Summary: 
Author: Paul Spooren
Author-email: mail@aparcar.org
Requires-Python: >=3.8,<4.0
Classifier: Programming Language :: Python :: 3
Classifier: Programming Language :: Python :: 3.8
Classifier: Programming Language :: Python :: 3.9
Classifier: Programming Language :: Python :: 3.10
Classifier: Programming Language :: Python :: 3.11
Requires-Dist: Flask (>=2.3.3,<3.0.0)
Requires-Dist: PyYAML (>=6.0.1,<7.0.0)
Requires-Dist: bcrypt (>=3.2.0,<4.0.0)
Requires-Dist: cffi (>=1.16.0,<2.0.0)
Requires-Dist: peewee (>=3.16.3,<4.0.0)
Requires-Dist: phonenumbers (>=8.12.31,<9.0.0)
Requires-Dist: python-slugify (>=5.0.2,<6.0.0)
Requires-Dist: six (>=1.16.0,<2.0.0)
